README.md
setup.py
logger/__init__.py
logger/config.py
logger/logger.py
logger_via.egg-info/PKG-INFO
logger_via.egg-info/SOURCES.txt
logger_via.egg-info/dependency_links.txt
logger_via.egg-info/top_level.txt