Metadata-Version: 2.1
Name: logger-via
Version: 1.0.2
Summary: Logging decorators (file or email)
Requires-Python: >=3.6
